flask_moreshell/__init__.py
flask_moreshell/__main__.py
flask_moreshell/py.typed
flask_moreshell/shells/__init__.py
flask_moreshell/shells/base_shell.py
flask_moreshell/shells/bpython_shell.py
flask_moreshell/shells/ipython_shell.py
flask_moreshell/shells/ptpython_shell.py
flask_moreshell/shells/python_shell.py
flask_moreshell-0.1.5.dist-info/LICENSE
flask_moreshell-0.1.5.dist-info/METADATA
flask_moreshell-0.1.5.dist-info/WHEEL
flask_moreshell-0.1.5.dist-info/entry_points.txt
flask_moreshell-0.1.5.dist-info/RECORD
