Metadata-Version: 2.1
Name: flask-moreshell
Version: 0.1.5
Summary: Flask Moreshell
Home-page: https://github.com/tgoddessana/flask-moreshell
License: MIT
Author: JAEGYUN JUNG
Author-email: twicegoddessana1229@gmail.com
Requires-Python: >=3.9,<4.0
Classifier: Development Status :: 4 - Beta
Classifier: License :: OSI Approved :: MIT License
Classifier: Programming Language :: Python :: 3
Classifier: Programming Language :: Python :: 3.9
Classifier: Programming Language :: Python :: 3.10
Classifier: Programming Language :: Python :: 3.11
Classifier: Programming Language :: Python :: 3.12
Provides-Extra: all
Provides-Extra: bpython
Provides-Extra: ipython
Provides-Extra: ptpython
Requires-Dist: click (>=8.0.1)
Project-URL: Changelog, https://github.com/tgoddessana/flask-moreshell/releases
Project-URL: Documentation, https://flask-moreshell.readthedocs.io
Project-URL: Repository, https://github.com/tgoddessana/flask-moreshell
